fast_views/__init__.py
fast_views/inner_join.py
fast_views-0.1.0.dist-info/WHEEL
fast_views-0.1.0.dist-info/METADATA
fast_views-0.1.0.dist-info/RECORD
